Makefile_venv/LICENSE
Makefile_venv/Makefile.venv
Makefile_venv/README.md
Makefile_venv/__init__.py
Makefile.venv-2023.4.17.dist-info/LICENSE
Makefile.venv-2023.4.17.dist-info/METADATA
Makefile.venv-2023.4.17.dist-info/WHEEL
Makefile.venv-2023.4.17.dist-info/entry_points.txt
Makefile.venv-2023.4.17.dist-info/top_level.txt
Makefile.venv-2023.4.17.dist-info/RECORD
