Metadata-Version: 2.1
Name: Makefile.venv
Version: 2023.4.17
Summary: Seamlessly manage Python virtual environment with a Makefile
Home-page: https://github.com/sio/Makefile.venv
License: Apache-2.0
Keywords: makefile,virtualenv,env
Classifier: Environment :: Console
Classifier: Intended Audience :: Developers
Classifier: Intended Audience :: System Administrators
Classifier: License :: OSI Approved :: Apache Software License
License-File: src/Makefile_venv/LICENSE
